 {
   "no_token": {
      "summary": "no access token",
      "value": {
         "detail": "Request auth header must contain bearer iDP access_token for authentication"
      }
   },
   "invalid_or_expired_token": {
      "summary": "Invalid or expired access token",
      "value": {
         "detail": "invalid or expired access token credentials"
      }
   },
   "no_corresponding_user": {
      "summary": "No corresponding user in db",
      "value": {
         "detail": "user is unauthenticated"
      }
   }
}